.gitattributes
.gitignore
LICENSE
README.md
package.json
setup.py
nativemessaging/__init__.py
nativemessaging/__main__.py
nativemessaging/install.py
nativemessaging/nativemessaging.py
nativemessaging/version.py
nativemessaging_ng.egg-info/PKG-INFO
nativemessaging_ng.egg-info/SOURCES.txt
nativemessaging_ng.egg-info/dependency_links.txt
nativemessaging_ng.egg-info/entry_points.txt
nativemessaging_ng.egg-info/top_level.txt
test/example_message
test/test-manifest.json
test/test.py
test/test.sh
test/test.t