Metadata-Version: 2.1
Name: nativemessaging-ng
Version: 1.3.3
Summary: A package with basic native messaging apis for webextensions
Home-page: https://github.com/roelderickx/nativemessaging-ng
Author: Rayquaza01, Roel Derickx
Author-email: nativemessaging-ng.pypi@derickx.be
License: MPL 2.0 License
Classifier: Programming Language :: Python :: 3
Classifier: License :: OSI Approved :: Mozilla Public License 2.0 (MPL 2.0)
Classifier: Operating System :: OS Independent
Requires-Python: >=3.0
License-File: LICENSE
